twcdirector/__init__.py
twcdirector/device.py
twcdirector/listener.py
twcdirector/protocol.py
twcdirector/utility.py
twcdirector/collectors/__init__.py
twcdirector/collectors/logfile.py
twc_director-0.0.1.dist-info/LICENSE
twc_director-0.0.1.dist-info/METADATA
twc_director-0.0.1.dist-info/WHEEL
twc_director-0.0.1.dist-info/top_level.txt
twc_director-0.0.1.dist-info/RECORD
