Metadata-Version: 2.1
Name: twc-director
Version: 0.0.1
Summary: Tesla Wall Charger Communication Library
Home-page: https://github.com/wired-square/twc-director
Author: Garth Berry
Author-email: garth@wiredsquare.com
License: UNKNOWN
Platform: UNKNOWN
Classifier: Programming Language :: Python :: 3
Classifier: License :: OSI Approved :: MIT License
Classifier: Operating System :: OS Independent
Requires-Python: >=3.8
License-File: LICENSE
Requires-Dist: aioserial
